brainpy/brainpy.py
brainpy/_speedup.cpython-310-darwin.so
brainpy/__init__.py
brainpy/_speedup.pxd
brainpy/_speedup.pyx
brainpy/_speedup.c
brainpy/mass_dict.py
brainpy/composition.py
brainpy/_c/compat.pxd
brainpy/_c/isotopic_constants.c
brainpy/_c/double_vector.cpython-310-darwin.so
brainpy/_c/isotopic_constants.pyx
brainpy/_c/isotopic_distribution.pyx
brainpy/_c/double_vector.c
brainpy/_c/double_vector.pyx
brainpy/_c/composition.cpython-310-darwin.so
brainpy/_c/__init__.py
brainpy/_c/isotopic_distribution.cpython-310-darwin.so
brainpy/_c/composition.pxd
brainpy/_c/composition.pyx
brainpy/_c/isotopic_distribution.c
brainpy/_c/compat.h
brainpy/_c/double_vector.pxd
brainpy/_c/isotopic_distribution.pxd
brainpy/_c/isotopic_constants.cpython-310-darwin.so
brainpy/_c/isotopic_constants.pxd
brainpy/_c/composition.c
brain_isotopic_distribution-1.5.19.dist-info/RECORD
brain_isotopic_distribution-1.5.19.dist-info/WHEEL
brain_isotopic_distribution-1.5.19.dist-info/top_level.txt
brain_isotopic_distribution-1.5.19.dist-info/METADATA
brain_isotopic_distribution-1.5.19.dist-info/licenses/LICENSE
