Metadata-Version: 2.4
Name: brain-isotopic-distribution
Version: 1.5.19
Summary: Fast and efficient theoretical isotopic profile generation
Home-page: https://github.com/mobiusklein/brainpy
Author: Joshua Klein, Han Hu
Author-email: jaklein@bu.edu
Maintainer: Joshua Klein
Maintainer-email: jaklein@bu.edu
Project-URL: Bug Tracker, https://github.com/mobiusklein/brainpy/issues
Project-URL: Source Code, https://github.com/mobiusklein/brainpy
Project-URL: Documentation, http://mobiusklein.github.io/brainpy
Keywords: isotopic distribution,isotopic pattern
Classifier: Development Status :: 4 - Beta
Classifier: Intended Audience :: Science/Research
Classifier: License :: OSI Approved :: Apache Software License
Classifier: Topic :: Scientific/Engineering :: Bio-Informatics
License-File: LICENSE
Dynamic: author
Dynamic: author-email
Dynamic: classifier
Dynamic: description
Dynamic: description-content-type
Dynamic: home-page
Dynamic: keywords
Dynamic: license-file
Dynamic: maintainer
Dynamic: maintainer-email
Dynamic: project-url
Dynamic: summary
